lyrics_predictor/__init__.py
lyrics_predictor/clean_and_save.py
lyrics_predictor/get_urls_and_scrape.py
lyrics_predictor/lyrics_predictor.py
lyrics_predictor/vectorize_and_train.py
lyrics_predictor-0.1.0.dist-info/AUTHORS.rst
lyrics_predictor-0.1.0.dist-info/LICENSE
lyrics_predictor-0.1.0.dist-info/METADATA
lyrics_predictor-0.1.0.dist-info/WHEEL
lyrics_predictor-0.1.0.dist-info/top_level.txt
lyrics_predictor-0.1.0.dist-info/RECORD
