Metadata-Version: 2.1
Name: lyrics-predictor
Version: 0.1.0
Summary: scrape lytics and train a model to predict the artist
Home-page: https://github.com/Ayazdi/lyrics_predictor
Author: Amirali Yazdi
Author-email: amirali.yazdi@yahoo.com
License: MIT license
Keywords: lyrics_predictor
Platform: UNKNOWN
Classifier: Development Status :: 2 - Pre-Alpha
Classifier: Intended Audience :: Developers
Classifier: License :: OSI Approved :: MIT License
Classifier: Natural Language :: English
Classifier: Programming Language :: Python :: 3
Classifier: Programming Language :: Python :: 3.4
Classifier: Programming Language :: Python :: 3.5
Classifier: Programming Language :: Python :: 3.6
Classifier: Programming Language :: Python :: 3.7
